applipy_healthcheck/__init__.py
applipy_healthcheck/endpoint.py
applipy_healthcheck/healthchecker.py
applipy_healthcheck/module.py
applipy_healthcheck/version.py
applipy_healthcheck-0.2.0.dist-info/LICENSE
applipy_healthcheck-0.2.0.dist-info/METADATA
applipy_healthcheck-0.2.0.dist-info/WHEEL
applipy_healthcheck-0.2.0.dist-info/top_level.txt
applipy_healthcheck-0.2.0.dist-info/RECORD
