Metadata-Version: 2.1
Name: applipy-healthcheck
Version: 0.2.0
Summary: Exposes an http endpoint exposing the health status of the app
Home-page: https://gitlab.com/applipy/applipy_healthcheck
Author: Alessio Linares
Author-email: mail@alessio.cc
License: Apache 2.0
Project-URL: Source, https://gitlab.com/applipy/applipy_healthcheck
Platform: UNKNOWN
Classifier: Development Status :: 5 - Production/Stable
Classifier: Intended Audience :: Developers
Classifier: License :: OSI Approved :: Apache Software License
Classifier: Programming Language :: Python :: 3.8
Classifier: Programming Language :: Python :: 3.9
Classifier: Topic :: Software Development :: Libraries
Requires-Python: >=3.8
Requires-Dist: applipy-http (<3.0.0,>=2.0.0)
